sortinghat/__init__.py
sortinghat/model_loading.py
sortinghat/pylib.py
sortinghat/resources/compressed_rf.pbz2
sortinghat/resources/dictionaryName.pkl
sortinghat/resources/dictionarySample.pkl
sortinghatinf/__init__.py
sortinghatinf/model_loading.py
sortinghatinf/pylib.py
sortinghatinf/resources/compressed_rf.pbz2
sortinghatinf/resources/dictionaryName.pkl
sortinghatinf/resources/dictionarySample.pkl
sortinghatinf-0.0.7.dist-info/LICENSE
sortinghatinf-0.0.7.dist-info/METADATA
sortinghatinf-0.0.7.dist-info/WHEEL
sortinghatinf-0.0.7.dist-info/top_level.txt
sortinghatinf-0.0.7.dist-info/RECORD
