Metadata-Version: 2.1
Name: sortinghatinf
Version: 0.0.7
Summary: A library that executes SortingHat feature type inference on Pandas dataframes
Home-page: https://github.com/bobotran/SortingHatLib
Author: Vraj Shah
Author-email: pvn251@gmail.com
License: MIT
Requires-Python: >=3.6
License-File: LICENSE
Requires-Dist: pandas
Requires-Dist: numpy (<1.24)
Requires-Dist: nltk
Requires-Dist: joblib
Requires-Dist: scikit-learn (==1.2.2)
